[
    {
        "model": "models_app.product",
        "pk": 1,
        "fields": {
            "type": "CPU",
            "man_id": 1,
            "views": 396,
            "name": "Intel Core i5-9600K",
            "description": "So crisp",
            "price": 300,
            "warranty": "1 week",
            "img_url": "https://c1.neweggimages.com/NeweggImage/ProductImageCompressAll300/19-117-959-V01.jpg?ex=2",
            "datetime_created": "2020-02-01 21:02:34.981315",
            "datetime_modified": "2020-02-01 21:02:34.981315"
        }
    },
    {
        "model": "models_app.product",
        "pk": 2,
        "fields": {
            "type": "GPU",
            "man_id": 5,
            "views": 200,
            "name": "Nvidia RTX 2080 Ti",
            "description": "Epicly powerful",
            "price": 500,
            "warranty": "3 weeks",
            "img_url": "https://c1.neweggimages.com/NeweggImage/ProductImage/A17P_1_201901291412355579.jpg?ex=2",
            "datetime_created": "2020-02-02 21:02:34.981315",
            "datetime_modified": "2020-02-03 21:02:34.981315"
        }
    },
    {
        "model": "models_app.product",
        "pk": 3,
        "fields": {
            "type": "Monitor",
            "man_id": 2,
            "views": 800,
            "name": "Asus VG278QR 27'",
            "description": "Crisp colors",
            "price": 290,
            "warranty": "2 weeks",
            "img_url": "https://c1.neweggimages.com/NeweggImage/ProductImage/24-236-313-V01.jpg",
            "datetime_created": "2020-02-04 21:02:34.981315",
            "datetime_modified": "2020-02-04 21:02:34.981315"
        }
    },
    {
        "model": "models_app.product",
        "pk": 4,
        "fields": {
            "type": "Keyboard",
            "man_id": 3,
            "views": 670,
            "name": "Corsair Gaming K55",
            "description": "Clickity clack",
            "price": 50,
            "warranty": "4 weeks",
            "img_url": "https://c1.neweggimages.com/ProductImageCompressAll300/23-816-083-V07.jpg?ex=2",
            "datetime_created": "2020-03-02 21:02:34.981315",
            "datetime_modified": "2020-03-02 21:02:34.981315"
        }
    },
    {
        "model": "models_app.product",
        "pk": 5,
        "fields": {
            "type": "RAM",
            "man_id": 4,
            "views": 100,
            "name": "HyperX Fury 8GB RAM ",
            "description": "DDR3 1600 (PC3 12800)|Timing 10-10-10|CAS Latency 10|Voltage 1.5V",
            "price": 70,
            "warranty": "2 weeks",
            "img_url": "https://c1.neweggimages.com/ProductImageCompressAll300/A4YU_1_20190829514152450.jpg?ex=2",
            "datetime_created": "2020-01-03 21:02:34.981315",
            "datetime_modified": "2020-01-03 21:02:34.981315"
        }
    }
]